pyproject_toml_api/version_api/__init__.py
pyproject_toml_api/version_api/version.py
pyproject_toml_api-0.1.0.dist-info/LICENSE
pyproject_toml_api-0.1.0.dist-info/METADATA
pyproject_toml_api-0.1.0.dist-info/WHEEL
pyproject_toml_api-0.1.0.dist-info/RECORD
